sciscripttools/__init__.py
sciscripttools/arguments.py
sciscripttools/checks.py
sciscripttools/common_code.py
sciscripttools/conversion.py
sciscripttools/generic.py
sciscripttools/io.py
sciscripttools/plot.py
sciscripttools/plot_defaults.py
sciscripttools-0.2.2.dist-info/LICENSE.md
sciscripttools-0.2.2.dist-info/METADATA
sciscripttools-0.2.2.dist-info/WHEEL
sciscripttools-0.2.2.dist-info/top_level.txt
sciscripttools-0.2.2.dist-info/RECORD
