Metadata-Version: 2.1
Name: sciscripttools
Version: 0.2.2
Summary: Small set of tools and functions for scientific code and scripts.
Home-page: UNKNOWN
Author: lifelemons
Author-email: 
License: UNKNOWN
Platform: UNKNOWN
Classifier: Programming Language :: Python :: 3
Classifier: License :: OSI Approved :: GNU General Public License v3 (GPLv3)
Classifier: Operating System :: OS Independent
